.eslintrc.yml
.prettierrc
CHANGES.md
LICENSE
MANIFEST.in
Makefile
README.md
babel.ini
increment_version.sh
pyproject.toml
run-js-linter.sh
run-tests.sh
setup.cfg
setup.py
.tx/config
invenio_theme_kth/__init__.py
invenio_theme_kth/config.py
invenio_theme_kth/ext.py
invenio_theme_kth/views.py
invenio_theme_kth/webpack.py
invenio_theme_kth.egg-info/PKG-INFO
invenio_theme_kth.egg-info/SOURCES.txt
invenio_theme_kth.egg-info/dependency_links.txt
invenio_theme_kth.egg-info/entry_points.txt
invenio_theme_kth.egg-info/not-zip-safe
invenio_theme_kth.egg-info/requires.txt
invenio_theme_kth.egg-info/top_level.txt
invenio_theme_kth/assets/semantic-ui/js/invenio_theme_kth/deposit/RDMDepositFormOverride.js
invenio_theme_kth/assets/semantic-ui/js/invenio_theme_kth/deposit/index.js
invenio_theme_kth/assets/semantic-ui/less/invenio_theme_kth/theme.config
invenio_theme_kth/assets/semantic-ui/translations/invenio_app_rdm/i18next-scanner.config.js
invenio_theme_kth/assets/semantic-ui/translations/invenio_app_rdm/i18next.js
invenio_theme_kth/assets/semantic-ui/translations/invenio_app_rdm/package-lock.json
invenio_theme_kth/assets/semantic-ui/translations/invenio_app_rdm/package.json
invenio_theme_kth/assets/semantic-ui/translations/invenio_app_rdm/translations.pot
invenio_theme_kth/assets/semantic-ui/translations/invenio_app_rdm/messages/index.js
invenio_theme_kth/assets/semantic-ui/translations/invenio_app_rdm/messages/en/translations.json
invenio_theme_kth/assets/semantic-ui/translations/invenio_app_rdm/messages/sv/messages.po
invenio_theme_kth/assets/semantic-ui/translations/invenio_app_rdm/messages/sv/translations.json
invenio_theme_kth/assets/semantic-ui/translations/invenio_app_rdm/scripts/compileCatalog.js
invenio_theme_kth/assets/semantic-ui/translations/invenio_app_rdm/scripts/initCatalog.js
invenio_theme_kth/static/documents/KTH-terms-of-use-en.pdf
invenio_theme_kth/static/documents/KTH-terms-of-use-sv.pdf
invenio_theme_kth/templates/semantic-ui/invenio_app_rdm/records/deposit_override.html
invenio_theme_kth/translations/messages.pot
invenio_theme_kth/translations/sv/LC_MESSAGES/messages.po
invenio_theme_kth/utils/registration_form.py
tests/__init__.py
tests/test_invenio_theme_kth.py